LCF/__init__.py
LCF/api_handler.py
LCF/autoscaler.py
LCF/bootstrap.py
LCF/cli.py
LCF/cli_configure.py
LCF/cli_init.py
LCF/dsl_parser.py
LCF/intelligent_router.py
LCF/orchestration.py
LCF/policy_engine.py
LCF/pool_manager.py
LCF/resource_resolver.py
LCF/secret_store.py
LCF/stack_manager.py
LCF/store.py
LCF/tasks.py
LCF/utils.py
LCF/cloud_adapters/__init__.py
LCF/cloud_adapters/aws_adapter.py
LCF/cloud_adapters/azure_adapter.py
LCF/cloud_adapters/gcp_adapter.py
LCF/cloud_adapters/noop.py
LCF/cloud_adapters/noop_adapter.py
LCF/cloud_adapters/opentofu_adapter.py
LCF/cloud_adapters/protocol.py
LCF/cloud_adapters/pulumi_adapter.py
LCF/cloud_adapters/test_manager_dispatch.py
LCF/cloud_adapters/test_opentofu_streaming.py
cloudbrew-1.2.0.dist-info/METADATA
cloudbrew-1.2.0.dist-info/WHEEL
cloudbrew-1.2.0.dist-info/entry_points.txt
cloudbrew-1.2.0.dist-info/top_level.txt
cloudbrew-1.2.0.dist-info/RECORD
